p_unity/FORTH.py
p_unity/__init__.py
p_unity/cli.py
p_unity/STD/F_CONTROL.py
p_unity/STD/F_CURSES.py
p_unity/STD/F_DSTACK.py
p_unity/STD/F_FIGLET.py
p_unity/STD/F_IO.py
p_unity/STD/F_JSON.py
p_unity/STD/F_MATH.py
p_unity/STD/F_NUCLEUS.py
p_unity/STD/F_OBJECT.py
p_unity/STD/F_REPL.py
p_unity/STD/F_TEST.py
p_unity/STD/__init__.py
tests/__init__.py
tests/test_forth.py
p_unity-0.42.202104180000.dist-info/LICENSE.md
p_unity-0.42.202104180000.dist-info/METADATA
p_unity-0.42.202104180000.dist-info/WHEEL
p_unity-0.42.202104180000.dist-info/entry_points.txt
p_unity-0.42.202104180000.dist-info/top_level.txt
p_unity-0.42.202104180000.dist-info/RECORD
