Metadata-Version: 2.1
Name: p-unity
Version: 0.42.202104180000
Summary: { Programming : Unity }
Home-page: https://github.com/p-unity
Author: Scott McCallum (https://sr.ht/~scott91e1)
Author-email: 262464@195387.com
License: UNKNOWN
Platform: UNKNOWN
Classifier: License :: Free To Use But Restricted
Classifier: Development Status :: 3 - Alpha
Classifier: Environment :: Console
Classifier: Environment :: Console :: Curses
Classifier: Environment :: Win32 (MS Windows)
Classifier: Environment :: No Input/Output (Daemon)
Classifier: Framework :: Trio
Classifier: Operating System :: OS Independent
Classifier: Intended Audience :: Developers
Classifier: Intended Audience :: Science/Research
Classifier: Intended Audience :: End Users/Desktop
Classifier: Intended Audience :: System Administrators
Classifier: Natural Language :: English
Classifier: Programming Language :: Python :: 3
Classifier: Programming Language :: Python :: Implementation :: CPython
Classifier: Programming Language :: Python :: Implementation :: PyPy
Classifier: Programming Language :: SQL
Classifier: Programming Language :: Forth
Classifier: Programming Language :: Basic
Classifier: Programming Language :: JavaScript
Classifier: Programming Language :: Other Scripting Engines
Classifier: Topic :: Education
Classifier: Topic :: Multimedia
Classifier: Topic :: Internet
Classifier: Topic :: Software Development
Classifier: Topic :: Software Development :: Code Generators
Classifier: Topic :: Software Development :: Bug Tracking
Classifier: Topic :: Software Development :: Interpreters
Classifier: Topic :: Software Development :: Libraries
Classifier: Topic :: Software Development :: Pre-processors
Classifier: Topic :: Software Development :: User Interfaces
Classifier: Topic :: Software Development :: Version Control
Classifier: Topic :: System :: Software Distribution
Classifier: Topic :: Text Processing
Classifier: Topic :: Text Processing :: Markup :: Markdown
Requires-Python: >=3.7
Requires-Dist: simplejson
